MANIFEST.in
README.rst
setup.cfg
setup.py
cyquant/__init__.py
cyquant/ctypes.pxd
cyquant/dimensions.cpp
cyquant/dimensions.pxd
cyquant/dimensions.pyx
cyquant/format_quantity.py
cyquant/qmath.cpp
cyquant/qmath.pyx
cyquant/quantities.cpp
cyquant/quantities.pxd
cyquant/quantities.pyx
cyquant/si.py
cyquant/util.cpp
cyquant/util.pyx
cyquant.egg-info/PKG-INFO
cyquant.egg-info/SOURCES.txt
cyquant.egg-info/dependency_links.txt
cyquant.egg-info/not-zip-safe
cyquant.egg-info/requires.txt
cyquant.egg-info/top_level.txt