Metadata-Version: 2.1
Name: cyquant
Version: 1.0.0
Summary: cython dimensional analysis and unit tracking utility
Home-page: https://github.com/gechelberger/cyquant
Author: Greg Echelberger
Author-email: gechelberger@gmail.com
License: UNKNOWN
Keywords: c-extension,SI,units,quantities,dimensional analysis
Platform: UNKNOWN
Classifier: Programming Language :: Python
Classifier: License :: OSI Approved :: MIT License
Classifier: Topic :: Scientific/Engineering
Classifier: Intended Audience :: Developers
Classifier: Intended Audience :: Science/Research
Provides-Extra: tests
Provides-Extra: dev
